README.txt
plonetheme.greencommunity-configure.zcml
setup.cfg
setup.py
docs/HISTORY.txt
docs/INSTALL.txt
docs/LICENSE.GPL
docs/LICENSE.txt
plonetheme/__init__.py
plonetheme.greencommunity.egg-info/PKG-INFO
plonetheme.greencommunity.egg-info/SOURCES.txt
plonetheme.greencommunity.egg-info/dependency_links.txt
plonetheme.greencommunity.egg-info/entry_points.txt
plonetheme.greencommunity.egg-info/namespace_packages.txt
plonetheme.greencommunity.egg-info/not-zip-safe
plonetheme.greencommunity.egg-info/requires.txt
plonetheme.greencommunity.egg-info/top_level.txt
plonetheme/greencommunity/__init__.py
plonetheme/greencommunity/configure.zcml
plonetheme/greencommunity/profiles.zcml
plonetheme/greencommunity/setuphandlers.py
plonetheme/greencommunity/skins.zcml
plonetheme/greencommunity/tests.py
plonetheme/greencommunity/version.txt
plonetheme/greencommunity/browser/__init__.py
plonetheme/greencommunity/browser/configure.zcml
plonetheme/greencommunity/browser/interfaces.py
plonetheme/greencommunity/browser/viewlet.pt
plonetheme/greencommunity/browser/viewlets.py
plonetheme/greencommunity/browser/images/Thumbs.db
plonetheme/greencommunity/browser/images/h2.gif
plonetheme/greencommunity/browser/images/header.jpg
plonetheme/greencommunity/browser/images/nav-h.gif
plonetheme/greencommunity/browser/images/top-bg.gif
plonetheme/greencommunity/browser/images/topleft.gif
plonetheme/greencommunity/browser/images/topright.gif
plonetheme/greencommunity/browser/images/toptopbottom.gif
plonetheme/greencommunity/browser/images/toptopleft.fwx.png
plonetheme/greencommunity/browser/images/toptopleft.gif
plonetheme/greencommunity/browser/images/toptopleft.orig.gif
plonetheme/greencommunity/browser/stylesheets/main.css
plonetheme/greencommunity/browser/viewlets/community_title.pt
plonetheme/greencommunity/profiles/default/cssregistry.xml
plonetheme/greencommunity/profiles/default/import_steps.xml
plonetheme/greencommunity/profiles/default/jsregistry.xml
plonetheme/greencommunity/profiles/default/plonetheme.greencommunity_various.txt
plonetheme/greencommunity/profiles/default/skins.xml
plonetheme/greencommunity/profiles/default/viewlets.xml
plonetheme/greencommunity/skins/plonetheme_greencommunity_custom_images/greencommunitynull.png
plonetheme/greencommunity/skins/plonetheme_greencommunity_custom_templates/greencommunitynull.pt
